examples/chunker.py
examples/config_example.py
examples/document_loaders.py
examples/embeddings.py
examples/entity_extraction_example.py
examples/graph_rag_ingestion.py
examples/graph_retriever_example.py
examples/tools.py
examples/vector_store.py
python_ragdoll-2.1.0.dist-info/licenses/LICENSE
ragdoll/__init__.py
ragdoll/app_config.py
ragdoll/cli.py
ragdoll/ragdoll.py
ragdoll/settings.py
ragdoll/cache/cache_manager.py
ragdoll/chunkers/__init__.py
ragdoll/config/__init__.py
ragdoll/config/base_config.py
ragdoll/config/config_manager.py
ragdoll/embeddings/__init__.py
ragdoll/entity_extraction/__init__.py
ragdoll/entity_extraction/base.py
ragdoll/entity_extraction/entity_extraction_service.py
ragdoll/entity_extraction/graph_persistence.py
ragdoll/entity_extraction/models.py
ragdoll/entity_extraction/relationship_parser.py
ragdoll/graph_stores/__init__.py
ragdoll/ingestion/__init__.py
ragdoll/ingestion/base.py
ragdoll/ingestion/document_loaders.py
ragdoll/ingestion/pipeline.py
ragdoll/llms/__init__.py
ragdoll/llms/callers.py
ragdoll/metrics/metrics_manager.py
ragdoll/pipeline/__init__.py
ragdoll/prompts/__init__.py
ragdoll/tools/search_tools.py
ragdoll/utils/__init__.py
ragdoll/utils/utils.py
ragdoll/vector_stores/__init__.py
ragdoll/vector_stores/base_vector_store.py
ragdoll/vector_stores/factory.py
tests/__init__.py
tests/conftest.py
tests/test_app_config.py
tests/test_cache_manager.py
tests/test_chunker.py
tests/test_embeddings.py
tests/test_entity_extraction_service.py
tests/test_graph_persistence.py
tests/test_graph_stores.py
tests/test_ingestion.py
tests/test_ingestion_service.py
tests/test_loader_registry.py
tests/test_metrics_manager.py
tests/test_pipeline_graph.py
tests/test_ragdoll.py
tests/test_ragdoll_integration.py
tests/test_relationship_parser.py
tests/test_vector_store_adapter.py
python_ragdoll-2.1.0.dist-info/METADATA
python_ragdoll-2.1.0.dist-info/WHEEL
python_ragdoll-2.1.0.dist-info/top_level.txt
python_ragdoll-2.1.0.dist-info/RECORD
