Metadata-Version: 2.4
Name: python-ragdoll
Version: 2.1.0
Summary: A set of helper classes that abstract some of the more common tasks of a typical RAG process including document loading/web scraping.
Author: Nathan Sasto
License: MIT
Classifier: Development Status :: 3 - Alpha
Classifier: Intended Audience :: Developers
Classifier: Topic :: Software Development :: Libraries :: Python Modules
Classifier: Topic :: Text Processing :: Markup :: Markdown
Classifier: Programming Language :: Python :: 3
Classifier: Programming Language :: Python :: 3.8
Classifier: Programming Language :: Python :: 3.9
Classifier: Programming Language :: Python :: 3.10
Classifier: Programming Language :: Python :: 3.11
Classifier: Programming Language :: Python :: 3.12
Classifier: License :: OSI Approved :: MIT License
Classifier: Operating System :: OS Independent
Requires-Python: >=3.8
License-File: LICENSE
Requires-Dist: langchain==1.0.5
Requires-Dist: langchain-openai==1.0.2
Requires-Dist: langchain-huggingface==1.0.1
Requires-Dist: langchain-community==0.4.1
Requires-Dist: langchain-chroma==1.0.0
Requires-Dist: chromadb==1.3.4
Requires-Dist: langchain-core==1.0.4
Requires-Dist: langsmith==0.4.42
Requires-Dist: langchain-google-community==3.0.0
Requires-Dist: langchain-text-splitters==1.0.0
Requires-Dist: langchain-markitdown==0.1.6
Requires-Dist: openai>=1.40.0
Requires-Dist: python-dotenv==1.0.1
Requires-Dist: retry==0.9.2
Requires-Dist: flask==3.0.0
Requires-Dist: flask-cors==4.0.0
Provides-Extra: dev
Requires-Dist: pytest==9.0.0; extra == "dev"
Requires-Dist: coverage; extra == "dev"
Requires-Dist: black; extra == "dev"
Requires-Dist: isort; extra == "dev"
Requires-Dist: flake8; extra == "dev"
Provides-Extra: entity
Requires-Dist: spacy>=3.7.0; extra == "entity"
Requires-Dist: spacy-transformers; extra == "entity"
Requires-Dist: sentence_transformers>=2.2.2; extra == "entity"
Requires-Dist: PyMuPDF>=1.25.5; extra == "entity"
Provides-Extra: graph
Requires-Dist: neo4j>=5.11.0; extra == "graph"
Requires-Dist: rdflib; extra == "graph"
Provides-Extra: all
Requires-Dist: python-ragdoll[dev,entity,graph]; extra == "all"
Dynamic: license-file
